sportsref/__init__.py
sportsref/decorators.py
sportsref/nba/__init__.py
sportsref/nba/boxscores.py
sportsref/nba/pbp.py
sportsref/nba/players.py
sportsref/nba/seasons.py
sportsref/nba/teams.py
sportsref/nfl/__init__.py
sportsref/nfl/boxscores.py
sportsref/nfl/finders/GPF.py
sportsref/nfl/finders/PSF.py
sportsref/nfl/finders/__init__.py
sportsref/nfl/pbp.py
sportsref/nfl/players.py
sportsref/nfl/seasons.py
sportsref/nfl/teams.py
sportsref/nfl/winProb.py
sportsref/options.py
sportsref/utils.py
sportsref-0.13.0.dist-info/LICENSE
sportsref-0.13.0.dist-info/WHEEL
sportsref-0.13.0.dist-info/METADATA
sportsref-0.13.0.dist-info/RECORD
