Metadata-Version: 2.1
Name: sportsref
Version: 0.13.0
Summary: 
Author: Matt Goldberg
Author-email: matt.goldberg7@gmail.com
Requires-Python: >=3.6.1,<4.0.0
Classifier: Programming Language :: Python :: 3
Classifier: Programming Language :: Python :: 3.7
Classifier: Programming Language :: Python :: 3.8
Classifier: Programming Language :: Python :: 3.9
Requires-Dist: mementos (>=1.3.1,<2.0.0)
Requires-Dist: numexpr (>=2.7.1,<3.0.0)
Requires-Dist: numpy (>=1.19.4,<2.0.0)
Requires-Dist: pandas (>=1.1.4,<2.0.0)
Requires-Dist: pyquery (>=1.4.3,<2.0.0)
Requires-Dist: requests (>=2.25.0,<3.0.0)
